<?xml version="1.0" encoding="UTF-8"?>
<data_set type="com.retek.ride.rule.newmodel.RuleGroup">
  <attribute name="name">
    <value>MO_Seed</value>
  </attribute>
  <attribute name="description">
    <value>a rule group</value>
  </attribute>
  <attribute name="role">
    <value>user</value>
  </attribute>
  <data_model type="com.retek.ride.rule.newmodel.Rule">
    <attribute name="name">
      <value>MOIN_cmt_app0030</value>
    </attribute>
    <attribute name="description">
      <value>a rule</value>
    </attribute>
    <attribute name="creator">
      <value>user</value>
    </attribute>
    <data_model type="java.lang.String">
      <attribute name="name">
        <value>E0</value>
      </attribute>
      <attribute name="formula">
        <value>MOWpunelapsedB = if(now &gt; end &amp;&amp; today == -1, false, if(current &lt; today, false, true))</value>
      </attribute>
    </data_model>
  </data_model>
  <data_model type="com.retek.ride.rule.newmodel.Rule">
    <attribute name="name">
      <value>MOIN_cmt_app0038</value>
    </attribute>
    <attribute name="description">
      <value>a rule</value>
    </attribute>
    <attribute name="creator">
      <value>user</value>
    </attribute>
    <data_model type="java.lang.String">
      <attribute name="name">
        <value>E0</value>
      </attribute>
      <attribute name="formula">
        <value>MOWpunelapBOPB = if(now &gt; end &amp;&amp; today == -1, false, if(current &lt; today, false, true))</value>
      </attribute>
    </data_model>
  </data_model>
  <data_model type="com.retek.ride.rule.newmodel.Rule">
    <attribute name="name">
      <value>MODySeedTx_seed</value>
    </attribute>
    <attribute name="description">
      <value>a rule</value>
    </attribute>
    <attribute name="creator">
      <value>user</value>
    </attribute>
    <data_model type="java.lang.String">
      <attribute name="name">
        <value>E0</value>
      </attribute>
      <attribute name="formula">
        <value>MODySeedTx = MOWpSeedTx</value>
      </attribute>
    </data_model>
  </data_model>
  <data_model type="com.retek.ride.rule.newmodel.Rule">
    <attribute name="name">
      <value>MOseed0013</value>
    </attribute>
    <attribute name="description">
      <value>a rule</value>
    </attribute>
    <data_model type="java.lang.String">
      <attribute name="name">
        <value>E0</value>
      </attribute>
      <attribute name="formula">
        <value>MOWPSeedDt = if(MOWpSeedB &amp;&amp; MOWpunelapsedB &amp;&amp; MOWpSeedTx !="0", now, ignore)</value>
      </attribute>
    </data_model>
  </data_model>
  <data_model type="com.retek.ride.rule.newmodel.Rule">
    <attribute name="name">
      <value>MOcalc0057</value>
    </attribute>
    <attribute name="description">
      <value>a rule</value>
    </attribute>
    <attribute name="creator">
      <value>user</value>
    </attribute>
    <data_model type="java.lang.String">
      <attribute name="name">
        <value>E0</value>
      </attribute>
      <attribute name="formula">
        <value>MOWpMessage1Tx = if(MOWpSeedB, "导入成功！","未选择导入数据源")</value>
      </attribute>
    </data_model>
  </data_model>
  <data_model type="com.retek.ride.rule.newmodel.Rule">
    <attribute name="name">
      <value>MOWpSlsARegR_temp</value>
    </attribute>
    <attribute name="description">
      <value>a rule</value>
    </attribute>
    <attribute name="creator">
      <value>user</value>
    </attribute>
    <data_model type="java.lang.String">
      <attribute name="name">
        <value>E0</value>
      </attribute>
      <attribute name="formula">
        <value>MOWpSlsARegTempR.level([clnd].[year]+[prod].[dvsn]+[loc].[area]+[seas].top) = TDTTSlsARegR</value>
      </attribute>
    </data_model>
  </data_model>
  <data_model type="com.retek.ride.rule.newmodel.Rule">
    <attribute name="name">
      <value>MOWpSlsRegTempR_temp</value>
    </attribute>
    <attribute name="description">
      <value>a rule</value>
    </attribute>
    <attribute name="creator">
      <value>user</value>
    </attribute>
    <data_model type="java.lang.String">
      <attribute name="name">
        <value>E0</value>
      </attribute>
      <attribute name="formula">
        <value>MOWpSlsRegTempR.level([clnd].[year]+[prod].[dvsn]+[loc].[area]+[seas].top) = TDTTSlsRegR</value>
      </attribute>
    </data_model>
  </data_model>
  <data_model type="com.retek.ride.rule.newmodel.Rule">
    <attribute name="name">
      <value>MOWpSlsRegTempC_temp</value>
    </attribute>
    <attribute name="description">
      <value>a rule</value>
    </attribute>
    <attribute name="creator">
      <value>user</value>
    </attribute>
    <data_model type="java.lang.String">
      <attribute name="name">
        <value>E0</value>
      </attribute>
      <attribute name="formula">
        <value>MOWpSlsRegTempC.level([clnd].[year]+[prod].[dvsn]+[loc].[area]+[seas].top)  = TDTTSlsRegC</value>
      </attribute>
    </data_model>
  </data_model>
  <data_model type="com.retek.ride.rule.newmodel.Rule">
    <attribute name="name">
      <value>MOWpMkdPermTempR_temp</value>
    </attribute>
    <attribute name="description">
      <value>a rule</value>
    </attribute>
    <attribute name="creator">
      <value>user</value>
    </attribute>
    <data_model type="java.lang.String">
      <attribute name="name">
        <value>E0</value>
      </attribute>
      <attribute name="formula">
        <value>MOWpMkdPermTempR .level([clnd].[year]+[prod].[dvsn]+[loc].[area]+[seas].top) = TDTTSlsRegR-TDTTSlsARegR</value>
      </attribute>
    </data_model>
  </data_model>
  <data_model type="com.retek.ride.rule.newmodel.Rule">
    <attribute name="name">
      <value>MO_seed0002</value>
    </attribute>
    <attribute name="description">
      <value>a rule</value>
    </attribute>
    <attribute name="creator">
      <value>user</value>
    </attribute>
    <data_model type="java.lang.String">
      <attribute name="name">
        <value>E0</value>
      </attribute>
      <attribute name="formula">
        <value>MOWpSlsARegR= if(MOWpunelapsedB &amp;&amp; MOWpSeedB,if(MOWpSeedTx == "1",MOWpSlsARegTempR,ignore),ignore)</value>
      </attribute>
    </data_model>
  </data_model>
  <data_model type="com.retek.ride.rule.newmodel.Rule">
    <attribute name="name">
      <value>MOWpSlsRegC_Seed</value>
    </attribute>
    <attribute name="description">
      <value>a rule</value>
    </attribute>
    <attribute name="creator">
      <value>user</value>
    </attribute>
    <data_model type="java.lang.String">
      <attribute name="name">
        <value>E0</value>
      </attribute>
      <attribute name="formula">
        <value>MOWpSlsRegC = if(MOWpunelapsedB &amp;&amp; MOWpSeedB,if(MOWpSeedTx == "1",MOWpSlsRegTempC,ignore),ignore)</value>
      </attribute>
    </data_model>
  </data_model>
  <data_model type="com.retek.ride.rule.newmodel.Rule">
    <attribute name="name">
      <value>MOWpSlsRegR_seed</value>
    </attribute>
    <attribute name="description">
      <value>a rule</value>
    </attribute>
    <attribute name="creator">
      <value>user</value>
    </attribute>
    <data_model type="java.lang.String">
      <attribute name="name">
        <value>E0</value>
      </attribute>
      <attribute name="formula">
        <value>MOWpSlsRegR = if(MOWpunelapsedB &amp;&amp; MOWpSeedB,if(MOWpSeedTx == "1",MOWpSlsRegTempR,ignore),ignore)</value>
      </attribute>
    </data_model>
  </data_model>
  <data_model type="com.retek.ride.rule.newmodel.Rule">
    <attribute name="name">
      <value>MOWpMkdPermR_seed</value>
    </attribute>
    <attribute name="description">
      <value>a rule</value>
    </attribute>
    <attribute name="creator">
      <value>user</value>
    </attribute>
    <data_model type="java.lang.String">
      <attribute name="name">
        <value>E0</value>
      </attribute>
      <attribute name="formula">
        <value>MOWpMkdPermR = if(MOWpunelapsedB &amp;&amp; MOWpSeedB,MOWpSlsRegR-MOWpSlsARegR,ignore)</value>
      </attribute>
    </data_model>
  </data_model>
  <data_model type="com.retek.ride.rule.newmodel.Rule">
    <attribute name="name">
      <value>MO_seed0007</value>
    </attribute>
    <attribute name="description">
      <value>a rule</value>
    </attribute>
    <attribute name="creator">
      <value>user</value>
    </attribute>
    <data_model type="java.lang.String">
      <attribute name="name">
        <value>E0</value>
      </attribute>
      <attribute name="formula">
        <value>MOWpMkdPermRp = if(MOWpunelapsedB &amp;&amp; MOWpSeedB,MOWpMkdPermR/MOWpSlsRegR,ignore)</value>
      </attribute>
    </data_model>
  </data_model>
  <data_model type="com.retek.ride.rule.newmodel.Rule">
    <attribute name="name">
      <value>MO_GMRegp_seed</value>
    </attribute>
    <attribute name="description">
      <value>a rule</value>
    </attribute>
    <attribute name="creator">
      <value>user</value>
    </attribute>
    <data_model type="java.lang.String">
      <attribute name="name">
        <value>E0</value>
      </attribute>
      <attribute name="formula">
        <value>MOWpGMRegp = if(MOWpunelapsedB &amp;&amp; MOWpSeedB,1-MOWpSlsRegC/MOWpSlsRegR,ignore)</value>
      </attribute>
    </data_model>
  </data_model>
  <data_model type="com.retek.ride.rule.newmodel.Rule">
    <attribute name="name">
      <value>MO_cmtseeddt</value>
    </attribute>
    <attribute name="description">
      <value>a rule</value>
    </attribute>
    <attribute name="creator">
      <value>user</value>
    </attribute>
    <data_model type="java.lang.String">
      <attribute name="name">
        <value>E0</value>
      </attribute>
      <attribute name="formula">
        <value>MOWpSeedDt.master = if (MOWpunelapsedB, MOWpSeedDt, ignore)</value>
      </attribute>
    </data_model>
  </data_model>
  <data_model type="com.retek.ride.rule.newmodel.Rule">
    <attribute name="name">
      <value>MODySeedTx_cmt</value>
    </attribute>
    <attribute name="description">
      <value>a rule</value>
    </attribute>
    <attribute name="creator">
      <value>user</value>
    </attribute>
    <data_model type="java.lang.String">
      <attribute name="name">
        <value>E0</value>
      </attribute>
      <attribute name="formula">
        <value>MODySeedTx.master = MODySeedTx</value>
      </attribute>
    </data_model>
  </data_model>
</data_set>
