<?xml version="1.0" encoding="UTF-8"?>
<data_set type="com.retek.ride.rule.newmodel.RuleGroup">
  <attribute name="name">
    <value>CM_load</value>
  </attribute>
  <attribute name="description">
    <value>a rule group</value>
  </attribute>
  <attribute name="role">
    <value>load</value>
  </attribute>
  <data_model type="com.retek.ride.rule.newmodel.Rule">
    <attribute name="name">
      <value>drdvspacer1tx_ld</value>
    </attribute>
    <attribute name="description">
      <value>a rule</value>
    </attribute>
    <attribute name="creator">
      <value>user</value>
    </attribute>
    <data_model type="java.lang.String">
      <attribute name="name">
        <value>E0</value>
      </attribute>
      <attribute name="formula">
        <value>DRDVSpacer1Tx = ""</value>
      </attribute>
    </data_model>
  </data_model>
  <data_model type="com.retek.ride.rule.newmodel.Rule">
    <attribute name="name">
      <value>drdvspacer2tx_ld</value>
    </attribute>
    <attribute name="description">
      <value>a rule</value>
    </attribute>
    <attribute name="creator">
      <value>user</value>
    </attribute>
    <data_model type="java.lang.String">
      <attribute name="name">
        <value>E0</value>
      </attribute>
      <attribute name="formula">
        <value>DRDVSpacer2Tx = ""</value>
      </attribute>
    </data_model>
  </data_model>
  <data_model type="com.retek.ride.rule.newmodel.Rule">
    <attribute name="name">
      <value>drdvspacer3tx_ld</value>
    </attribute>
    <attribute name="description">
      <value>a rule</value>
    </attribute>
    <attribute name="creator">
      <value>user</value>
    </attribute>
    <data_model type="java.lang.String">
      <attribute name="name">
        <value>E0</value>
      </attribute>
      <attribute name="formula">
        <value>DRDVSpacer3Tx = ""</value>
      </attribute>
    </data_model>
  </data_model>
  <data_model type="com.retek.ride.rule.newmodel.Rule">
    <attribute name="name">
      <value>drdvspacer4tx_ld</value>
    </attribute>
    <attribute name="description">
      <value>a rule</value>
    </attribute>
    <attribute name="creator">
      <value>user</value>
    </attribute>
    <data_model type="java.lang.String">
      <attribute name="name">
        <value>E0</value>
      </attribute>
      <attribute name="formula">
        <value>DRDVSpacer4Tx = ""</value>
      </attribute>
    </data_model>
  </data_model>
  <data_model type="com.retek.ride.rule.newmodel.Rule">
    <attribute name="name">
      <value>drdvspacer5tx_ld</value>
    </attribute>
    <attribute name="description">
      <value>a rule</value>
    </attribute>
    <attribute name="creator">
      <value>user</value>
    </attribute>
    <data_model type="java.lang.String">
      <attribute name="name">
        <value>E0</value>
      </attribute>
      <attribute name="formula">
        <value>DRDVSpacer5Tx = ""</value>
      </attribute>
    </data_model>
  </data_model>
  <data_model type="com.retek.ride.rule.newmodel.Rule">
    <attribute name="name">
      <value>drdvelapsedu_ld</value>
    </attribute>
    <attribute name="description">
      <value>a rule</value>
    </attribute>
    <attribute name="creator">
      <value>user</value>
    </attribute>
    <data_model type="java.lang.String">
      <attribute name="name">
        <value>E0</value>
      </attribute>
      <attribute name="formula">
        <value>DRDVElapsedU = prefer(today - 1, if(now &lt; end &amp;&amp; now &gt; begin , last, if(now &gt; end, last, -1)))</value>
      </attribute>
    </data_model>
  </data_model>
  <data_model type="com.retek.ride.rule.newmodel.Rule">
    <attribute name="name">
      <value>elapsed</value>
    </attribute>
    <attribute name="description">
      <value>a rule</value>
    </attribute>
    <attribute name="creator">
      <value>user</value>
    </attribute>
    <data_model type="java.lang.String">
      <attribute name="name">
        <value>E0</value>
      </attribute>
      <attribute name="formula">
        <value>elapsed = DRDVElapsedU.pst</value>
      </attribute>
    </data_model>
  </data_model>
  <data_model type="com.retek.ride.rule.newmodel.Rule">
    <attribute name="name">
      <value>drdvelapsedb_ld</value>
    </attribute>
    <attribute name="description">
      <value>a rule</value>
    </attribute>
    <attribute name="creator">
      <value>user</value>
    </attribute>
    <data_model type="java.lang.String">
      <attribute name="name">
        <value>E0</value>
      </attribute>
      <attribute name="formula">
        <value>DRDVElapsedB = if(now &gt; end &amp;&amp; today == -1, false, if(current &lt; today, true , false))</value>
      </attribute>
    </data_model>
  </data_model>
  <data_model type="com.retek.ride.rule.newmodel.Rule">
    <attribute name="name">
      <value>cmwpappropb_ld</value>
    </attribute>
    <attribute name="description">
      <value>a rule</value>
    </attribute>
    <attribute name="creator">
      <value>user</value>
    </attribute>
    <data_model type="java.lang.String">
      <attribute name="name">
        <value>E0</value>
      </attribute>
      <attribute name="formula">
        <value>CMWPApprOPB = FALSE</value>
      </attribute>
    </data_model>
  </data_model>
  <data_model type="com.retek.ride.rule.newmodel.Rule">
    <attribute name="name">
      <value>cmwpapproveoptx_ld</value>
    </attribute>
    <attribute name="description">
      <value>a rule</value>
    </attribute>
    <attribute name="creator">
      <value>user</value>
    </attribute>
    <data_model type="java.lang.String">
      <attribute name="name">
        <value>E0</value>
      </attribute>
      <attribute name="formula">
        <value>CMWPApprOPTx = CMWPApprOPTx.master</value>
      </attribute>
    </data_model>
  </data_model>
  <data_model type="com.retek.ride.rule.newmodel.Rule">
    <attribute name="name">
      <value>cmwpapproveopdt_ld</value>
    </attribute>
    <attribute name="description">
      <value>a rule</value>
    </attribute>
    <attribute name="creator">
      <value>user</value>
    </attribute>
    <data_model type="java.lang.String">
      <attribute name="name">
        <value>E0</value>
      </attribute>
      <attribute name="formula">
        <value>CMWPApprOPDt = CMWPApprOPDt.master</value>
      </attribute>
    </data_model>
  </data_model>
  <data_model type="com.retek.ride.rule.newmodel.Rule">
    <attribute name="name">
      <value>cmwpapproveopby_ld</value>
    </attribute>
    <attribute name="description">
      <value>a rule</value>
    </attribute>
    <attribute name="creator">
      <value>user</value>
    </attribute>
    <data_model type="java.lang.String">
      <attribute name="name">
        <value>E0</value>
      </attribute>
      <attribute name="formula">
        <value>CMWPApprOPBy = CMWPApprOPBy.master</value>
      </attribute>
    </data_model>
  </data_model>
  <data_model type="com.retek.ride.rule.newmodel.Rule">
    <attribute name="name">
      <value>cmwpsdslsb_ld</value>
    </attribute>
    <attribute name="description">
      <value>a rule</value>
    </attribute>
    <attribute name="creator">
      <value>user</value>
    </attribute>
    <data_model type="java.lang.String">
      <attribute name="name">
        <value>E0</value>
      </attribute>
      <attribute name="formula">
        <value>CMWPSdSlsB = FALSE</value>
      </attribute>
    </data_model>
  </data_model>
  <data_model type="com.retek.ride.rule.newmodel.Rule">
    <attribute name="name">
      <value>cmwpsdslstx_ld</value>
    </attribute>
    <attribute name="description">
      <value>a rule</value>
    </attribute>
    <attribute name="creator">
      <value>user</value>
    </attribute>
    <data_model type="java.lang.String">
      <attribute name="name">
        <value>E0</value>
      </attribute>
      <attribute name="formula">
        <value>CMWPSdSlsTx = CMWPSdSlsTx.master</value>
      </attribute>
    </data_model>
  </data_model>
  <data_model type="com.retek.ride.rule.newmodel.Rule">
    <attribute name="name">
      <value>cmwpsdslsdt_ld</value>
    </attribute>
    <attribute name="description">
      <value>a rule</value>
    </attribute>
    <attribute name="creator">
      <value>user</value>
    </attribute>
    <data_model type="java.lang.String">
      <attribute name="name">
        <value>E0</value>
      </attribute>
      <attribute name="formula">
        <value>CMWPSdSlsDt = CMWPSdSlsDt.master</value>
      </attribute>
    </data_model>
  </data_model>
  <data_model type="com.retek.ride.rule.newmodel.Rule">
    <attribute name="name">
      <value>cmwpsdslsby_ld</value>
    </attribute>
    <attribute name="description">
      <value>a rule</value>
    </attribute>
    <attribute name="creator">
      <value>user</value>
    </attribute>
    <data_model type="java.lang.String">
      <attribute name="name">
        <value>E0</value>
      </attribute>
      <attribute name="formula">
        <value>CMWPSdSlsBy = CMWPSdSlsBy.master</value>
      </attribute>
    </data_model>
  </data_model>
  <data_model type="com.retek.ride.rule.newmodel.Rule">
    <attribute name="name">
      <value>cmlyslsr_ld</value>
    </attribute>
    <attribute name="description">
      <value>a rule</value>
    </attribute>
    <attribute name="creator">
      <value>user</value>
    </attribute>
    <data_model type="java.lang.String">
      <attribute name="name">
        <value>E0</value>
      </attribute>
      <attribute name="formula">
        <value>CMLYSlsR &lt;- timeshift(CMWPSlsR.master, ADLYWeekMapTx.master)</value>
      </attribute>
    </data_model>
  </data_model>
  <data_model type="com.retek.ride.rule.newmodel.Rule">
    <attribute name="name">
      <value>cmlyslsu_ld</value>
    </attribute>
    <attribute name="description">
      <value>a rule</value>
    </attribute>
    <attribute name="creator">
      <value>user</value>
    </attribute>
    <data_model type="java.lang.String">
      <attribute name="name">
        <value>E0</value>
      </attribute>
      <attribute name="formula">
        <value>CMLYSlsU &lt;- timeshift(CMWPSlsU.master, ADLYWeekMapTx.master)</value>
      </attribute>
    </data_model>
  </data_model>
  <data_model type="com.retek.ride.rule.newmodel.Rule">
    <attribute name="name">
      <value>cmwpslsr_ld</value>
    </attribute>
    <attribute name="description">
      <value>a rule</value>
    </attribute>
    <attribute name="creator">
      <value>user</value>
    </attribute>
    <data_model type="java.lang.String">
      <attribute name="name">
        <value>E0</value>
      </attribute>
      <attribute name="formula">
        <value>CMWPSlsR = CMWPSlsR.master</value>
      </attribute>
    </data_model>
  </data_model>
  <data_model type="com.retek.ride.rule.newmodel.Rule">
    <attribute name="name">
      <value>cmwpslsu_ld</value>
    </attribute>
    <attribute name="description">
      <value>a rule</value>
    </attribute>
    <attribute name="creator">
      <value>user</value>
    </attribute>
    <data_model type="java.lang.String">
      <attribute name="name">
        <value>E0</value>
      </attribute>
      <attribute name="formula">
        <value>CMWPSlsU = CMWPSlsU.master</value>
      </attribute>
    </data_model>
  </data_model>
  <data_model type="com.retek.ride.rule.newmodel.Rule">
    <attribute name="name">
      <value>cmopslsr_ld</value>
    </attribute>
    <attribute name="description">
      <value>a rule</value>
    </attribute>
    <attribute name="creator">
      <value>user</value>
    </attribute>
    <data_model type="java.lang.String">
      <attribute name="name">
        <value>E0</value>
      </attribute>
      <attribute name="formula">
        <value>CMOPSlsR = CMOPSlsR.master</value>
      </attribute>
    </data_model>
  </data_model>
  <data_model type="com.retek.ride.rule.newmodel.Rule">
    <attribute name="name">
      <value>cmopslsu_ld</value>
    </attribute>
    <attribute name="description">
      <value>a rule</value>
    </attribute>
    <attribute name="creator">
      <value>user</value>
    </attribute>
    <data_model type="java.lang.String">
      <attribute name="name">
        <value>E0</value>
      </attribute>
      <attribute name="formula">
        <value>CMOPSlsU = CMOPSlsU.master</value>
      </attribute>
    </data_model>
  </data_model>
  <data_model type="com.retek.ride.rule.newmodel.Rule">
    <attribute name="name">
      <value>cmlygpr_ld</value>
    </attribute>
    <attribute name="description">
      <value>a rule</value>
    </attribute>
    <attribute name="creator">
      <value>user</value>
    </attribute>
    <data_model type="java.lang.String">
      <attribute name="name">
        <value>E0</value>
      </attribute>
      <attribute name="formula">
        <value>CMLYGPR &lt;- timeshift(CMWPGPR.master, ADLYWeekMapTx.master)</value>
      </attribute>
    </data_model>
  </data_model>
  <data_model type="com.retek.ride.rule.newmodel.Rule">
    <attribute name="name">
      <value>cmwpgpr_ld</value>
    </attribute>
    <attribute name="description">
      <value>a rule</value>
    </attribute>
    <attribute name="creator">
      <value>user</value>
    </attribute>
    <data_model type="java.lang.String">
      <attribute name="name">
        <value>E0</value>
      </attribute>
      <attribute name="formula">
        <value>CMWPGPR = CMWPGPR.master</value>
      </attribute>
    </data_model>
  </data_model>
  <data_model type="com.retek.ride.rule.newmodel.Rule">
    <attribute name="name">
      <value>cmopgpr_ld</value>
    </attribute>
    <attribute name="description">
      <value>a rule</value>
    </attribute>
    <attribute name="creator">
      <value>user</value>
    </attribute>
    <data_model type="java.lang.String">
      <attribute name="name">
        <value>E0</value>
      </attribute>
      <attribute name="formula">
        <value>CMOPGPR = CMOPGPR.master</value>
      </attribute>
    </data_model>
  </data_model>
  <data_model type="com.retek.ride.rule.newmodel.Rule">
    <attribute name="name">
      <value>cmlypvtlblslsr_ld</value>
    </attribute>
    <attribute name="description">
      <value>a rule</value>
    </attribute>
    <attribute name="creator">
      <value>user</value>
    </attribute>
    <data_model type="java.lang.String">
      <attribute name="name">
        <value>E0</value>
      </attribute>
      <attribute name="formula">
        <value>CMLYPvtLblSlsR &lt;- timeshift(CMWPPvtLblSlsR.master, ADLYWeekMapTx.master)</value>
      </attribute>
    </data_model>
  </data_model>
  <data_model type="com.retek.ride.rule.newmodel.Rule">
    <attribute name="name">
      <value>cmlypvtlblslsu_ld</value>
    </attribute>
    <attribute name="description">
      <value>a rule</value>
    </attribute>
    <attribute name="creator">
      <value>user</value>
    </attribute>
    <data_model type="java.lang.String">
      <attribute name="name">
        <value>E0</value>
      </attribute>
      <attribute name="formula">
        <value>CMLYPvtLblSlsU &lt;- timeshift(CMWPPvtLblSlsU.master, ADLYWeekMapTx.master)</value>
      </attribute>
    </data_model>
  </data_model>
  <data_model type="com.retek.ride.rule.newmodel.Rule">
    <attribute name="name">
      <value>cmwppvtlblslsr_ld</value>
    </attribute>
    <attribute name="description">
      <value>a rule</value>
    </attribute>
    <attribute name="creator">
      <value>user</value>
    </attribute>
    <data_model type="java.lang.String">
      <attribute name="name">
        <value>E0</value>
      </attribute>
      <attribute name="formula">
        <value>CMWPPvtLblSlsR = CMWPPvtLblSlsR.master</value>
      </attribute>
    </data_model>
  </data_model>
  <data_model type="com.retek.ride.rule.newmodel.Rule">
    <attribute name="name">
      <value>cmwppvtlblslsu_ld</value>
    </attribute>
    <attribute name="description">
      <value>a rule</value>
    </attribute>
    <attribute name="creator">
      <value>user</value>
    </attribute>
    <data_model type="java.lang.String">
      <attribute name="name">
        <value>E0</value>
      </attribute>
      <attribute name="formula">
        <value>CMWPPvtLblSlsU = CMWPPvtLblSlsU.master</value>
      </attribute>
    </data_model>
  </data_model>
  <data_model type="com.retek.ride.rule.newmodel.Rule">
    <attribute name="name">
      <value>cmoppvtlblslsr_ld</value>
    </attribute>
    <attribute name="description">
      <value>a rule</value>
    </attribute>
    <attribute name="creator">
      <value>user</value>
    </attribute>
    <data_model type="java.lang.String">
      <attribute name="name">
        <value>E0</value>
      </attribute>
      <attribute name="formula">
        <value>CMOPPvtLblSlsR = CMOPPvtLblSlsR.master</value>
      </attribute>
    </data_model>
  </data_model>
  <data_model type="com.retek.ride.rule.newmodel.Rule">
    <attribute name="name">
      <value>cmoppvtlblslsu_ld</value>
    </attribute>
    <attribute name="description">
      <value>a rule</value>
    </attribute>
    <attribute name="creator">
      <value>user</value>
    </attribute>
    <data_model type="java.lang.String">
      <attribute name="name">
        <value>E0</value>
      </attribute>
      <attribute name="formula">
        <value>CMOPPvtLblSlsU = CMOPPvtLblSlsU.master</value>
      </attribute>
    </data_model>
  </data_model>
  <data_model type="com.retek.ride.rule.newmodel.Rule">
    <attribute name="name">
      <value>cmlypvtlblgpr_ld</value>
    </attribute>
    <attribute name="description">
      <value>a rule</value>
    </attribute>
    <attribute name="creator">
      <value>user</value>
    </attribute>
    <data_model type="java.lang.String">
      <attribute name="name">
        <value>E0</value>
      </attribute>
      <attribute name="formula">
        <value>CMLYPvtLblGPR &lt;- timeshift(CMWPPvtLblGPR.master, ADLYWeekMapTx.master)</value>
      </attribute>
    </data_model>
  </data_model>
  <data_model type="com.retek.ride.rule.newmodel.Rule">
    <attribute name="name">
      <value>cmwppvtlblgpr_ld</value>
    </attribute>
    <attribute name="description">
      <value>a rule</value>
    </attribute>
    <attribute name="creator">
      <value>user</value>
    </attribute>
    <data_model type="java.lang.String">
      <attribute name="name">
        <value>E0</value>
      </attribute>
      <attribute name="formula">
        <value>CMWPPvtLblGPR = CMWPPvtLblGPR.master</value>
      </attribute>
    </data_model>
  </data_model>
  <data_model type="com.retek.ride.rule.newmodel.Rule">
    <attribute name="name">
      <value>cmoppvtlblgpr_ld</value>
    </attribute>
    <attribute name="description">
      <value>a rule</value>
    </attribute>
    <attribute name="creator">
      <value>user</value>
    </attribute>
    <data_model type="java.lang.String">
      <attribute name="name">
        <value>E0</value>
      </attribute>
      <attribute name="formula">
        <value>CMOPPvtLblGPR = CMOPPvtLblGPR.master</value>
      </attribute>
    </data_model>
  </data_model>
  <data_model type="com.retek.ride.rule.newmodel.Rule">
    <attribute name="name">
      <value>cmlypromoslsr_ld</value>
    </attribute>
    <attribute name="description">
      <value>a rule</value>
    </attribute>
    <attribute name="creator">
      <value>user</value>
    </attribute>
    <data_model type="java.lang.String">
      <attribute name="name">
        <value>E0</value>
      </attribute>
      <attribute name="formula">
        <value>CMLYPromoSlsR &lt;- timeshift(CMWPPromoSlsR.master, ADLYWeekMapTx.master)</value>
      </attribute>
    </data_model>
  </data_model>
  <data_model type="com.retek.ride.rule.newmodel.Rule">
    <attribute name="name">
      <value>cmlypromoslsu_ld</value>
    </attribute>
    <attribute name="description">
      <value>a rule</value>
    </attribute>
    <attribute name="creator">
      <value>user</value>
    </attribute>
    <data_model type="java.lang.String">
      <attribute name="name">
        <value>E0</value>
      </attribute>
      <attribute name="formula">
        <value>CMLYPromoSlsU &lt;- timeshift(CMWPPromoSlsU.master, ADLYWeekMapTx.master)</value>
      </attribute>
    </data_model>
  </data_model>
  <data_model type="com.retek.ride.rule.newmodel.Rule">
    <attribute name="name">
      <value>cmwppromoslsr_ld</value>
    </attribute>
    <attribute name="description">
      <value>a rule</value>
    </attribute>
    <attribute name="creator">
      <value>user</value>
    </attribute>
    <data_model type="java.lang.String">
      <attribute name="name">
        <value>E0</value>
      </attribute>
      <attribute name="formula">
        <value>CMWPPromoSlsR = CMWPPromoSlsR.master</value>
      </attribute>
    </data_model>
  </data_model>
  <data_model type="com.retek.ride.rule.newmodel.Rule">
    <attribute name="name">
      <value>cmwppromoslsu_ld</value>
    </attribute>
    <attribute name="description">
      <value>a rule</value>
    </attribute>
    <attribute name="creator">
      <value>user</value>
    </attribute>
    <data_model type="java.lang.String">
      <attribute name="name">
        <value>E0</value>
      </attribute>
      <attribute name="formula">
        <value>CMWPPromoSlsU = CMWPPromoSlsU.master</value>
      </attribute>
    </data_model>
  </data_model>
  <data_model type="com.retek.ride.rule.newmodel.Rule">
    <attribute name="name">
      <value>cmoppromoslsr_ld</value>
    </attribute>
    <attribute name="description">
      <value>a rule</value>
    </attribute>
    <attribute name="creator">
      <value>user</value>
    </attribute>
    <data_model type="java.lang.String">
      <attribute name="name">
        <value>E0</value>
      </attribute>
      <attribute name="formula">
        <value>CMOPPromoSlsR = CMOPPromoSlsR.master</value>
      </attribute>
    </data_model>
  </data_model>
  <data_model type="com.retek.ride.rule.newmodel.Rule">
    <attribute name="name">
      <value>cmoppromoslsu_ld</value>
    </attribute>
    <attribute name="description">
      <value>a rule</value>
    </attribute>
    <attribute name="creator">
      <value>user</value>
    </attribute>
    <data_model type="java.lang.String">
      <attribute name="name">
        <value>E0</value>
      </attribute>
      <attribute name="formula">
        <value>CMOPPromoSlsU = CMOPPromoSlsU.master</value>
      </attribute>
    </data_model>
  </data_model>
  <data_model type="com.retek.ride.rule.newmodel.Rule">
    <attribute name="name">
      <value>cmlyavginvr_ld</value>
    </attribute>
    <attribute name="description">
      <value>a rule</value>
    </attribute>
    <attribute name="creator">
      <value>user</value>
    </attribute>
    <data_model type="java.lang.String">
      <attribute name="name">
        <value>E0</value>
      </attribute>
      <attribute name="formula">
        <value>CMLYAvgInvR &lt;- timeshift(CMWPAvgInvR.master, ADLYWeekMapTx.master)</value>
      </attribute>
    </data_model>
  </data_model>
  <data_model type="com.retek.ride.rule.newmodel.Rule">
    <attribute name="name">
      <value>cmwpavginvr_ld</value>
    </attribute>
    <attribute name="description">
      <value>a rule</value>
    </attribute>
    <attribute name="creator">
      <value>user</value>
    </attribute>
    <data_model type="java.lang.String">
      <attribute name="name">
        <value>E0</value>
      </attribute>
      <attribute name="formula">
        <value>CMWPAvgInvR = CMWPAvgInvR.master</value>
      </attribute>
    </data_model>
  </data_model>
  <data_model type="com.retek.ride.rule.newmodel.Rule">
    <attribute name="name">
      <value>cmopavginvr_ld</value>
    </attribute>
    <attribute name="description">
      <value>a rule</value>
    </attribute>
    <attribute name="creator">
      <value>user</value>
    </attribute>
    <data_model type="java.lang.String">
      <attribute name="name">
        <value>E0</value>
      </attribute>
      <attribute name="formula">
        <value>CMOPAvgInvR = CMOPAvgInvR.master</value>
      </attribute>
    </data_model>
  </data_model>
  <data_model type="com.retek.ride.rule.newmodel.Rule">
    <attribute name="name">
      <value>cmlymkttahhv_ld</value>
    </attribute>
    <attribute name="description">
      <value>a rule</value>
    </attribute>
    <attribute name="creator">
      <value>user</value>
    </attribute>
    <data_model type="java.lang.String">
      <attribute name="name">
        <value>E0</value>
      </attribute>
      <attribute name="formula">
        <value>CMDVMktTAHHp = DRTYMktTAHHp.master</value>
      </attribute>
    </data_model>
  </data_model>
  <data_model type="com.retek.ride.rule.newmodel.Rule">
    <attribute name="name">
      <value>cmlyrtlttahhv_ld</value>
    </attribute>
    <attribute name="description">
      <value>a rule</value>
    </attribute>
    <attribute name="creator">
      <value>user</value>
    </attribute>
    <data_model type="java.lang.String">
      <attribute name="name">
        <value>E0</value>
      </attribute>
      <attribute name="formula">
        <value>CMDVRtlTAHHp = DRTYRtlTAHHp.master</value>
      </attribute>
    </data_model>
  </data_model>
  <data_model type="com.retek.ride.rule.newmodel.Rule">
    <attribute name="name">
      <value>cmdvmkttaspndp_ld</value>
    </attribute>
    <attribute name="description">
      <value>a rule</value>
    </attribute>
    <attribute name="creator">
      <value>user</value>
    </attribute>
    <data_model type="java.lang.String">
      <attribute name="name">
        <value>E0</value>
      </attribute>
      <attribute name="formula">
        <value>CMDVMktTASpndp = DRTYMktTASpndp.master</value>
      </attribute>
    </data_model>
  </data_model>
  <data_model type="com.retek.ride.rule.newmodel.Rule">
    <attribute name="name">
      <value>cmdvrtltaspndp_ld</value>
    </attribute>
    <attribute name="description">
      <value>a rule</value>
    </attribute>
    <attribute name="creator">
      <value>user</value>
    </attribute>
    <data_model type="java.lang.String">
      <attribute name="name">
        <value>E0</value>
      </attribute>
      <attribute name="formula">
        <value>CMDVRtlTASpndp = DRTYRtlTASpndp.master</value>
      </attribute>
    </data_model>
  </data_model>
  <data_model type="com.retek.ride.rule.newmodel.Rule">
    <attribute name="name">
      <value>cmwptgtshpktatx_ld</value>
    </attribute>
    <attribute name="description">
      <value>a rule</value>
    </attribute>
    <attribute name="creator">
      <value>user</value>
    </attribute>
    <data_model type="java.lang.String">
      <attribute name="name">
        <value>E0</value>
      </attribute>
      <attribute name="formula">
        <value>CMWPTgtShpKTATx = CMWPTgtShpKTATx.master</value>
      </attribute>
    </data_model>
  </data_model>
  <data_model type="com.retek.ride.rule.newmodel.Rule">
    <attribute name="name">
      <value>cmdvttlshopperx_ld</value>
    </attribute>
    <attribute name="description">
      <value>a rule</value>
    </attribute>
    <attribute name="creator">
      <value>user</value>
    </attribute>
    <data_model type="java.lang.String">
      <attribute name="name">
        <value>E0</value>
      </attribute>
      <attribute name="formula">
        <value>CMDVTtlShopperX = DRTYTtlShopperX.master</value>
      </attribute>
    </data_model>
  </data_model>
  <data_model type="com.retek.ride.rule.newmodel.Rule">
    <attribute name="name">
      <value>cmdvshopfreqv_ld</value>
    </attribute>
    <attribute name="description">
      <value>a rule</value>
    </attribute>
    <attribute name="creator">
      <value>user</value>
    </attribute>
    <data_model type="java.lang.String">
      <attribute name="name">
        <value>E0</value>
      </attribute>
      <attribute name="formula">
        <value>CMDVShopFreqV = DRTYShopFreqV.master</value>
      </attribute>
    </data_model>
  </data_model>
  <data_model type="com.retek.ride.rule.newmodel.Rule">
    <attribute name="name">
      <value>cmdvnumcatbsktv_ld</value>
    </attribute>
    <attribute name="description">
      <value>a rule</value>
    </attribute>
    <attribute name="creator">
      <value>user</value>
    </attribute>
    <data_model type="java.lang.String">
      <attribute name="name">
        <value>E0</value>
      </attribute>
      <attribute name="formula">
        <value>CMDVNumCatBsktV = DRTYNumCatBsktV.master</value>
      </attribute>
    </data_model>
  </data_model>
  <data_model type="com.retek.ride.rule.newmodel.Rule">
    <attribute name="name">
      <value>cmdvavgbsktvalv_ld</value>
    </attribute>
    <attribute name="description">
      <value>a rule</value>
    </attribute>
    <attribute name="creator">
      <value>user</value>
    </attribute>
    <data_model type="java.lang.String">
      <attribute name="name">
        <value>E0</value>
      </attribute>
      <attribute name="formula">
        <value>CMDVAvgBsktValV = DRTYAvgBsktValV.master</value>
      </attribute>
    </data_model>
  </data_model>
  <data_model type="com.retek.ride.rule.newmodel.Rule">
    <attribute name="name">
      <value>cmwptaoppktatx_ld</value>
    </attribute>
    <attribute name="description">
      <value>a rule</value>
    </attribute>
    <attribute name="creator">
      <value>user</value>
    </attribute>
    <data_model type="java.lang.String">
      <attribute name="name">
        <value>E0</value>
      </attribute>
      <attribute name="formula">
        <value>CMWPTAOppKTATx = CMWPTAOppKTATx.master</value>
      </attribute>
    </data_model>
  </data_model>
  <data_model type="com.retek.ride.rule.newmodel.Rule">
    <attribute name="name">
      <value>cmdvpentrp_ld</value>
    </attribute>
    <attribute name="description">
      <value>a rule</value>
    </attribute>
    <attribute name="creator">
      <value>user</value>
    </attribute>
    <data_model type="java.lang.String">
      <attribute name="name">
        <value>E0</value>
      </attribute>
      <attribute name="formula">
        <value>CMDVPentrp = DRTYPentrp.master</value>
      </attribute>
    </data_model>
  </data_model>
  <data_model type="com.retek.ride.rule.newmodel.Rule">
    <attribute name="name">
      <value>cmdvloyaltyp_ld</value>
    </attribute>
    <attribute name="description">
      <value>a rule</value>
    </attribute>
    <attribute name="creator">
      <value>user</value>
    </attribute>
    <data_model type="java.lang.String">
      <attribute name="name">
        <value>E0</value>
      </attribute>
      <attribute name="formula">
        <value>CMDVLoyaltyp = DRTYLoyaltyp.master</value>
      </attribute>
    </data_model>
  </data_model>
  <data_model type="com.retek.ride.rule.newmodel.Rule">
    <attribute name="name">
      <value>cmdvspendx_ld</value>
    </attribute>
    <attribute name="description">
      <value>a rule</value>
    </attribute>
    <attribute name="creator">
      <value>user</value>
    </attribute>
    <data_model type="java.lang.String">
      <attribute name="name">
        <value>E0</value>
      </attribute>
      <attribute name="formula">
        <value>CMDVSpendX = DRTYSpendX.master</value>
      </attribute>
    </data_model>
  </data_model>
  <data_model type="com.retek.ride.rule.newmodel.Rule">
    <attribute name="name">
      <value>cmwpcompktatx_ld</value>
    </attribute>
    <attribute name="description">
      <value>a rule</value>
    </attribute>
    <attribute name="creator">
      <value>user</value>
    </attribute>
    <data_model type="java.lang.String">
      <attribute name="name">
        <value>E0</value>
      </attribute>
      <attribute name="formula">
        <value>CMWPCompKTATx = CMWPCompKTATx.master</value>
      </attribute>
    </data_model>
  </data_model>
  <data_model type="com.retek.ride.rule.newmodel.Rule">
    <attribute name="name">
      <value>cmdvmktslsr_ld</value>
    </attribute>
    <attribute name="description">
      <value>a rule</value>
    </attribute>
    <attribute name="creator">
      <value>user</value>
    </attribute>
    <data_model type="java.lang.String">
      <attribute name="name">
        <value>E0</value>
      </attribute>
      <attribute name="formula">
        <value>CMDVMktSlsR = DRTYMktSlsR.master</value>
      </attribute>
    </data_model>
  </data_model>
  <data_model type="com.retek.ride.rule.newmodel.Rule">
    <attribute name="name">
      <value>cmdvmktslsu_ld</value>
    </attribute>
    <attribute name="description">
      <value>a rule</value>
    </attribute>
    <attribute name="creator">
      <value>user</value>
    </attribute>
    <data_model type="java.lang.String">
      <attribute name="name">
        <value>E0</value>
      </attribute>
      <attribute name="formula">
        <value>CMDVMktSlsU = DRTYMktSlsU.master</value>
      </attribute>
    </data_model>
  </data_model>
  <data_model type="com.retek.ride.rule.newmodel.Rule">
    <attribute name="name">
      <value>drlymktslsr_ld</value>
    </attribute>
    <attribute name="description">
      <value>a rule</value>
    </attribute>
    <attribute name="creator">
      <value>user</value>
    </attribute>
    <data_model type="java.lang.String">
      <attribute name="name">
        <value>E0</value>
      </attribute>
      <attribute name="formula">
        <value>CMLYMktSlsR = DRLYMktSlsR.master</value>
      </attribute>
    </data_model>
  </data_model>
  <data_model type="com.retek.ride.rule.newmodel.Rule">
    <attribute name="name">
      <value>cmlymktslsu_ld</value>
    </attribute>
    <attribute name="description">
      <value>a rule</value>
    </attribute>
    <attribute name="creator">
      <value>user</value>
    </attribute>
    <data_model type="java.lang.String">
      <attribute name="name">
        <value>E0</value>
      </attribute>
      <attribute name="formula">
        <value>CMLYMktSlsU = DRLYMktSlsU.master</value>
      </attribute>
    </data_model>
  </data_model>
  <data_model type="com.retek.ride.rule.newmodel.Rule">
    <attribute name="name">
      <value>cmdvmktpromoslsr_ld</value>
    </attribute>
    <attribute name="description">
      <value>a rule</value>
    </attribute>
    <attribute name="creator">
      <value>user</value>
    </attribute>
    <data_model type="java.lang.String">
      <attribute name="name">
        <value>E0</value>
      </attribute>
      <attribute name="formula">
        <value>CMDVMktPromoSlsR = DRTYMktPromoSlsR.master</value>
      </attribute>
    </data_model>
  </data_model>
  <data_model type="com.retek.ride.rule.newmodel.Rule">
    <attribute name="name">
      <value>cmdvmktpromoslsu_ld</value>
    </attribute>
    <attribute name="description">
      <value>a rule</value>
    </attribute>
    <attribute name="creator">
      <value>user</value>
    </attribute>
    <data_model type="java.lang.String">
      <attribute name="name">
        <value>E0</value>
      </attribute>
      <attribute name="formula">
        <value>CMDVMktPromoSlsU = DRTYMktPromoSlsU.master</value>
      </attribute>
    </data_model>
  </data_model>
  <data_model type="com.retek.ride.rule.newmodel.Rule">
    <attribute name="name">
      <value>cmlymktpromoslsr_ld</value>
    </attribute>
    <attribute name="description">
      <value>a rule</value>
    </attribute>
    <attribute name="creator">
      <value>user</value>
    </attribute>
    <data_model type="java.lang.String">
      <attribute name="name">
        <value>E0</value>
      </attribute>
      <attribute name="formula">
        <value>CMLYMktPromoSlsR = DRLYMktPromoSlsR.master</value>
      </attribute>
    </data_model>
  </data_model>
  <data_model type="com.retek.ride.rule.newmodel.Rule">
    <attribute name="name">
      <value>cmlymktpromoslsu_ld</value>
    </attribute>
    <attribute name="description">
      <value>a rule</value>
    </attribute>
    <attribute name="creator">
      <value>user</value>
    </attribute>
    <data_model type="java.lang.String">
      <attribute name="name">
        <value>E0</value>
      </attribute>
      <attribute name="formula">
        <value>CMLYMktPromoSlsU = DRLYMktPromoSlsU.master</value>
      </attribute>
    </data_model>
  </data_model>
  <data_model type="com.retek.ride.rule.newmodel.Rule">
    <attribute name="name">
      <value>cmdvmktturnrr_ld</value>
    </attribute>
    <attribute name="description">
      <value>a rule</value>
    </attribute>
    <attribute name="creator">
      <value>user</value>
    </attribute>
    <data_model type="java.lang.String">
      <attribute name="name">
        <value>E0</value>
      </attribute>
      <attribute name="formula">
        <value>CMDVMktTurnRr = DRTYMktTurnRr.master</value>
      </attribute>
    </data_model>
  </data_model>
  <data_model type="com.retek.ride.rule.newmodel.Rule">
    <attribute name="name">
      <value>drlymktturnrr_ld</value>
    </attribute>
    <attribute name="description">
      <value>a rule</value>
    </attribute>
    <attribute name="creator">
      <value>user</value>
    </attribute>
    <data_model type="java.lang.String">
      <attribute name="name">
        <value>E0</value>
      </attribute>
      <attribute name="formula">
        <value>CMLYMktTurnRr = DRLYMktTurnRr.master</value>
      </attribute>
    </data_model>
  </data_model>
  <data_model type="com.retek.ride.rule.newmodel.Rule">
    <attribute name="name">
      <value>cmfcslsr_ld</value>
    </attribute>
    <attribute name="description">
      <value>a rule</value>
    </attribute>
    <attribute name="creator">
      <value>user</value>
    </attribute>
    <data_model type="java.lang.String">
      <attribute name="name">
        <value>E0</value>
      </attribute>
      <attribute name="formula">
        <value>CMFcSlsR = CMFcSlsR.master</value>
      </attribute>
    </data_model>
  </data_model>
  <data_model type="com.retek.ride.rule.newmodel.Rule">
    <attribute name="name">
      <value>cmfcslsu_ld</value>
    </attribute>
    <attribute name="description">
      <value>a rule</value>
    </attribute>
    <attribute name="creator">
      <value>user</value>
    </attribute>
    <data_model type="java.lang.String">
      <attribute name="name">
        <value>E0</value>
      </attribute>
      <attribute name="formula">
        <value>CMFcSlsU = CMFcSlsU.master</value>
      </attribute>
    </data_model>
  </data_model>
  <data_model type="com.retek.ride.rule.newmodel.Rule">
    <attribute name="name">
      <value>cmdvprchfreqv_ld</value>
    </attribute>
    <attribute name="description">
      <value>a rule</value>
    </attribute>
    <attribute name="creator">
      <value>user</value>
    </attribute>
    <data_model type="java.lang.String">
      <attribute name="name">
        <value>E0</value>
      </attribute>
      <attribute name="formula">
        <value>CMDVPrchFreqV = DRTYPrchFreqV.master</value>
      </attribute>
    </data_model>
  </data_model>
  <data_model type="com.retek.ride.rule.newmodel.Rule">
    <attribute name="name">
      <value>cmdvitmtrpspbyerv_ld</value>
    </attribute>
    <attribute name="description">
      <value>a rule</value>
    </attribute>
    <attribute name="creator">
      <value>user</value>
    </attribute>
    <data_model type="java.lang.String">
      <attribute name="name">
        <value>E0</value>
      </attribute>
      <attribute name="formula">
        <value>CMDVItmTrpspByerV = DRTYItmTrpspByerL4V.master</value>
      </attribute>
    </data_model>
  </data_model>
  <data_model type="com.retek.ride.rule.newmodel.Rule">
    <attribute name="name">
      <value>cmdvitmrevpbyerv_ld</value>
    </attribute>
    <attribute name="description">
      <value>a rule</value>
    </attribute>
    <attribute name="creator">
      <value>user</value>
    </attribute>
    <data_model type="java.lang.String">
      <attribute name="name">
        <value>E0</value>
      </attribute>
      <attribute name="formula">
        <value>CMDVItmRevpByerV = DRTYItmRevpByerL4V.master</value>
      </attribute>
    </data_model>
  </data_model>
  <data_model type="com.retek.ride.rule.newmodel.Rule">
    <attribute name="name">
      <value>cmdvannlspndx_ld</value>
    </attribute>
    <attribute name="description">
      <value>a rule</value>
    </attribute>
    <attribute name="creator">
      <value>user</value>
    </attribute>
    <data_model type="java.lang.String">
      <attribute name="name">
        <value>E0</value>
      </attribute>
      <attribute name="formula">
        <value>CMDVAnnlSpndX = DRTYAnnlSpndX.master</value>
      </attribute>
    </data_model>
  </data_model>
  <data_model type="com.retek.ride.rule.newmodel.Rule">
    <attribute name="name">
      <value>drlyannlspndx_ld</value>
    </attribute>
    <attribute name="description">
      <value>a rule</value>
    </attribute>
    <attribute name="creator">
      <value>user</value>
    </attribute>
    <data_model type="java.lang.String">
      <attribute name="name">
        <value>E0</value>
      </attribute>
      <attribute name="formula">
        <value>CMLYAnnlSpndX = DRLYAnnlSpndX.master</value>
      </attribute>
    </data_model>
  </data_model>
  <data_model type="com.retek.ride.rule.newmodel.Rule">
    <attribute name="name">
      <value>cmdvitmpentrp_ld</value>
    </attribute>
    <attribute name="description">
      <value>a rule</value>
    </attribute>
    <attribute name="creator">
      <value>user</value>
    </attribute>
    <data_model type="java.lang.String">
      <attribute name="name">
        <value>E0</value>
      </attribute>
      <attribute name="formula">
        <value>CMDVItmPentrp = DRTYItmPentrp.master</value>
      </attribute>
    </data_model>
  </data_model>
  <data_model type="com.retek.ride.rule.newmodel.Rule">
    <attribute name="name">
      <value>cmdvitmspndpitmptrpv_ld</value>
    </attribute>
    <attribute name="description">
      <value>a rule</value>
    </attribute>
    <attribute name="creator">
      <value>user</value>
    </attribute>
    <data_model type="java.lang.String">
      <attribute name="name">
        <value>E0</value>
      </attribute>
      <attribute name="formula">
        <value>CMDVItmSpndpTrpV = DRTYItmSpndpTrpL4V.master</value>
      </attribute>
    </data_model>
  </data_model>
  <data_model type="com.retek.ride.rule.newmodel.Rule">
    <attribute name="name">
      <value>cmdvitmspndpromop_ld</value>
    </attribute>
    <attribute name="description">
      <value>a rule</value>
    </attribute>
    <attribute name="creator">
      <value>user</value>
    </attribute>
    <data_model type="java.lang.String">
      <attribute name="name">
        <value>E0</value>
      </attribute>
      <attribute name="formula">
        <value>CMDVItmSpndPromop = DRTYItmSpndPromoL4p.master</value>
      </attribute>
    </data_model>
  </data_model>
  <data_model type="com.retek.ride.rule.newmodel.Rule">
    <attribute name="name">
      <value>cmdvbyerconvrtv_ld</value>
    </attribute>
    <attribute name="description">
      <value>a rule</value>
    </attribute>
    <attribute name="creator">
      <value>user</value>
    </attribute>
    <data_model type="java.lang.String">
      <attribute name="name">
        <value>E0</value>
      </attribute>
      <attribute name="formula">
        <value>CMDVByerConvRtV = DRTYByerConvRtV.master</value>
      </attribute>
    </data_model>
  </data_model>
  <data_model type="com.retek.ride.rule.newmodel.Rule">
    <attribute name="name">
      <value>cmdvnumbsktwcatv_ld</value>
    </attribute>
    <attribute name="description">
      <value>a rule</value>
    </attribute>
    <attribute name="creator">
      <value>user</value>
    </attribute>
    <data_model type="java.lang.String">
      <attribute name="name">
        <value>E0</value>
      </attribute>
      <attribute name="formula">
        <value>CMDVNumBsktwCatV = DRTYNumBsktwCatV.master</value>
      </attribute>
    </data_model>
  </data_model>
  <data_model type="com.retek.ride.rule.newmodel.Rule">
    <attribute name="name">
      <value>cmlynumbsktwcatv_ld</value>
    </attribute>
    <attribute name="description">
      <value>a rule</value>
    </attribute>
    <attribute name="creator">
      <value>user</value>
    </attribute>
    <data_model type="java.lang.String">
      <attribute name="name">
        <value>E0</value>
      </attribute>
      <attribute name="formula">
        <value>CMLYNumBsktwCatV = DRLYNumBsktwCatV.master</value>
      </attribute>
    </data_model>
  </data_model>
  <data_model type="com.retek.ride.rule.newmodel.Rule">
    <attribute name="name">
      <value>cmdvtrnsszwcatv_ld</value>
    </attribute>
    <attribute name="description">
      <value>a rule</value>
    </attribute>
    <attribute name="creator">
      <value>user</value>
    </attribute>
    <data_model type="java.lang.String">
      <attribute name="name">
        <value>E0</value>
      </attribute>
      <attribute name="formula">
        <value>CMDVTrnsSzwCatV = DRTYTrnsSzwCatV.master</value>
      </attribute>
    </data_model>
  </data_model>
  <data_model type="com.retek.ride.rule.newmodel.Rule">
    <attribute name="name">
      <value>cmlytrnsszwcatv_ld</value>
    </attribute>
    <attribute name="description">
      <value>a rule</value>
    </attribute>
    <attribute name="creator">
      <value>user</value>
    </attribute>
    <data_model type="java.lang.String">
      <attribute name="name">
        <value>E0</value>
      </attribute>
      <attribute name="formula">
        <value>CMLYTrnsSzwCatV = DRLYTrnsSzwCatV.master</value>
      </attribute>
    </data_model>
  </data_model>
  <data_model type="com.retek.ride.rule.newmodel.Rule">
    <attribute name="name">
      <value>cmwptacticassgntx_ld</value>
    </attribute>
    <attribute name="description">
      <value>a rule</value>
    </attribute>
    <attribute name="creator">
      <value>user</value>
    </attribute>
    <data_model type="java.lang.String">
      <attribute name="name">
        <value>E0</value>
      </attribute>
      <attribute name="formula">
        <value>CMWPTacticAssgnTx = CMWPTacticAssgnTx.master</value>
      </attribute>
    </data_model>
  </data_model>
  <data_model type="com.retek.ride.rule.newmodel.Rule">
    <attribute name="name">
      <value>cmlytacticassgntx_ld</value>
    </attribute>
    <attribute name="description">
      <value>a rule</value>
    </attribute>
    <attribute name="creator">
      <value>user</value>
    </attribute>
    <data_model type="java.lang.String">
      <attribute name="name">
        <value>E0</value>
      </attribute>
      <attribute name="formula">
        <value>CMLYTacticAssgnTx &lt;-timeshift(CMWPTacticAssgnTx.master, ADLYQrtrMapTx.master)</value>
      </attribute>
    </data_model>
  </data_model>
  <data_model type="com.retek.ride.rule.newmodel.Rule">
    <attribute name="name">
      <value>cmwpstratassgntx_ld</value>
    </attribute>
    <attribute name="description">
      <value>a rule</value>
    </attribute>
    <attribute name="creator">
      <value>user</value>
    </attribute>
    <data_model type="java.lang.String">
      <attribute name="name">
        <value>E0</value>
      </attribute>
      <attribute name="formula">
        <value>CMWPStratAssgnTx = CMWPStratAssgnTx.master</value>
      </attribute>
    </data_model>
  </data_model>
  <data_model type="com.retek.ride.rule.newmodel.Rule">
    <attribute name="name">
      <value>cmlyprchfreqv_ld</value>
    </attribute>
    <attribute name="description">
      <value>a rule</value>
    </attribute>
    <attribute name="creator">
      <value>user</value>
    </attribute>
    <data_model type="java.lang.String">
      <attribute name="name">
        <value>E0</value>
      </attribute>
      <attribute name="formula">
        <value>CMLYPrchFreqV = DRLYPrchFreqV.master</value>
      </attribute>
    </data_model>
  </data_model>
  <data_model type="com.retek.ride.rule.newmodel.Rule">
    <attribute name="name">
      <value>cmlyitmpentrp_ld</value>
    </attribute>
    <attribute name="description">
      <value>a rule</value>
    </attribute>
    <attribute name="creator">
      <value>user</value>
    </attribute>
    <data_model type="java.lang.String">
      <attribute name="name">
        <value>E0</value>
      </attribute>
      <attribute name="formula">
        <value>CMLYItmPentrp = DRLYItmPentrp.master</value>
      </attribute>
    </data_model>
  </data_model>
  <data_model type="com.retek.ride.rule.newmodel.Rule">
    <attribute name="name">
      <value>cmfcprchfreqv_ld</value>
    </attribute>
    <attribute name="description">
      <value>a rule</value>
    </attribute>
    <attribute name="creator">
      <value>user</value>
    </attribute>
    <data_model type="java.lang.String">
      <attribute name="name">
        <value>E0</value>
      </attribute>
      <attribute name="formula">
        <value>CMFcPrchFreqV = CMFcPrchFreqV.master</value>
      </attribute>
    </data_model>
  </data_model>
  <data_model type="com.retek.ride.rule.newmodel.Rule">
    <attribute name="name">
      <value>cmfcitmpentrp_ld</value>
    </attribute>
    <attribute name="description">
      <value>a rule</value>
    </attribute>
    <attribute name="creator">
      <value>user</value>
    </attribute>
    <data_model type="java.lang.String">
      <attribute name="name">
        <value>E0</value>
      </attribute>
      <attribute name="formula">
        <value>CMFcItmPentrp = CMFcItmPentrp.master</value>
      </attribute>
    </data_model>
  </data_model>
  <data_model type="com.retek.ride.rule.newmodel.Rule">
    <attribute name="name">
      <value>cmfcslsc_ld</value>
    </attribute>
    <attribute name="description">
      <value>a rule</value>
    </attribute>
    <attribute name="creator">
      <value>user</value>
    </attribute>
    <data_model type="java.lang.String">
      <attribute name="name">
        <value>E0</value>
      </attribute>
      <attribute name="formula">
        <value>CMFcSlsC = CMFcSlsC.master</value>
      </attribute>
    </data_model>
  </data_model>
  <data_model type="com.retek.ride.rule.newmodel.Rule">
    <attribute name="name">
      <value>cmwpovrrolatx_calc</value>
    </attribute>
    <attribute name="description">
      <value>a rule</value>
    </attribute>
    <attribute name="creator">
      <value>user</value>
    </attribute>
    <data_model type="java.lang.String">
      <attribute name="name">
        <value>E0</value>
      </attribute>
      <attribute name="formula">
        <value>CMWPOvrRolATx = CMWPOvrRolATx.master</value>
      </attribute>
    </data_model>
  </data_model>
  <data_model type="com.retek.ride.rule.newmodel.Rule">
    <attribute name="name">
      <value>cmlyassgnrolatx_ld</value>
    </attribute>
    <attribute name="description">
      <value>a rule</value>
    </attribute>
    <attribute name="creator">
      <value>user</value>
    </attribute>
    <data_model type="java.lang.String">
      <attribute name="name">
        <value>E0</value>
      </attribute>
      <attribute name="formula">
        <value>CMLYAssgnRolATx &lt;- timeshift(CMWPAssgnRolATx.master, ADLYQrtrMapTx.master)</value>
      </attribute>
    </data_model>
  </data_model>
  <data_model type="com.retek.ride.rule.newmodel.Rule">
    <attribute name="name">
      <value>cmopassgnrolatx_ld</value>
    </attribute>
    <attribute name="description">
      <value>a rule</value>
    </attribute>
    <attribute name="creator">
      <value>user</value>
    </attribute>
    <data_model type="java.lang.String">
      <attribute name="name">
        <value>E0</value>
      </attribute>
      <attribute name="formula">
        <value>CMOPAssgnRolATx = CMOPAssgnRolATx.master</value>
      </attribute>
    </data_model>
  </data_model>
  <data_model type="com.retek.ride.rule.newmodel.Rule">
    <attribute name="name">
      <value>cmwpovrrolbtx_ld</value>
    </attribute>
    <attribute name="description">
      <value>a rule</value>
    </attribute>
    <attribute name="creator">
      <value>user</value>
    </attribute>
    <data_model type="java.lang.String">
      <attribute name="name">
        <value>E0</value>
      </attribute>
      <attribute name="formula">
        <value>CMWPOvrRolBTx = CMWPOvrRolBTx.master</value>
      </attribute>
    </data_model>
  </data_model>
  <data_model type="com.retek.ride.rule.newmodel.Rule">
    <attribute name="name">
      <value>cmlyassgnrolbtx_ld</value>
    </attribute>
    <attribute name="description">
      <value>a rule</value>
    </attribute>
    <attribute name="creator">
      <value>user</value>
    </attribute>
    <data_model type="java.lang.String">
      <attribute name="name">
        <value>E0</value>
      </attribute>
      <attribute name="formula">
        <value>CMLYAssgnRolBTx &lt;- timeshift(CMWPAssgnRolBTx.master, ADLYQrtrMapTx.master)</value>
      </attribute>
    </data_model>
  </data_model>
  <data_model type="com.retek.ride.rule.newmodel.Rule">
    <attribute name="name">
      <value>cmopassgnrolbtx_ld</value>
    </attribute>
    <attribute name="description">
      <value>a rule</value>
    </attribute>
    <attribute name="creator">
      <value>user</value>
    </attribute>
    <data_model type="java.lang.String">
      <attribute name="name">
        <value>E0</value>
      </attribute>
      <attribute name="formula">
        <value>CMOPAssgnRolBTx = CMOPAssgnRolBTx.master</value>
      </attribute>
    </data_model>
  </data_model>
  <data_model type="com.retek.ride.rule.newmodel.Rule">
    <attribute name="name">
      <value>cmlystratassgntx_ld</value>
    </attribute>
    <attribute name="description">
      <value>a rule</value>
    </attribute>
    <attribute name="creator">
      <value>user</value>
    </attribute>
    <data_model type="java.lang.String">
      <attribute name="name">
        <value>E0</value>
      </attribute>
      <attribute name="formula">
        <value>CMLYStratAssgnTx &lt;- timeshift(CMWPStratAssgnTx.master, ADLYQrtrMapTx.master)</value>
      </attribute>
    </data_model>
  </data_model>
  <data_model type="com.retek.ride.rule.newmodel.Rule">
    <attribute name="name">
      <value>cmopstratassgntx_ld</value>
    </attribute>
    <attribute name="description">
      <value>a rule</value>
    </attribute>
    <attribute name="creator">
      <value>user</value>
    </attribute>
    <data_model type="java.lang.String">
      <attribute name="name">
        <value>E0</value>
      </attribute>
      <attribute name="formula">
        <value>CMOPStratAssgnTx = CMOPStratAssgnTx.master</value>
      </attribute>
    </data_model>
  </data_model>
  <data_model type="com.retek.ride.rule.newmodel.Rule">
    <attribute name="name">
      <value>cmdvslsbycsr_ld</value>
    </attribute>
    <attribute name="description">
      <value>a rule</value>
    </attribute>
    <attribute name="creator">
      <value>user</value>
    </attribute>
    <data_model type="java.lang.String">
      <attribute name="name">
        <value>E0</value>
      </attribute>
      <attribute name="formula">
        <value>CMDVSlsbyCSR = CMWPSlsR * ADDVConSegDistV</value>
      </attribute>
    </data_model>
  </data_model>
  <data_model type="com.retek.ride.rule.newmodel.Rule">
    <attribute name="name">
      <value>cmdvslsbycsu_ld</value>
    </attribute>
    <attribute name="description">
      <value>a rule</value>
    </attribute>
    <attribute name="creator">
      <value>user</value>
    </attribute>
    <data_model type="java.lang.String">
      <attribute name="name">
        <value>E0</value>
      </attribute>
      <attribute name="formula">
        <value>CMDVSlsbyCSU = CMWPSlsU * ADDVConSegDistV</value>
      </attribute>
    </data_model>
  </data_model>
  <data_model type="com.retek.ride.rule.newmodel.Rule">
    <attribute name="name">
      <value>cmdvpromoslsbycsr_ld</value>
    </attribute>
    <attribute name="description">
      <value>a rule</value>
    </attribute>
    <attribute name="creator">
      <value>user</value>
    </attribute>
    <data_model type="java.lang.String">
      <attribute name="name">
        <value>E0</value>
      </attribute>
      <attribute name="formula">
        <value>CMDVPromoSlsbyCSR = CMWPPromoSlsR * ADDVConSegDistV</value>
      </attribute>
    </data_model>
  </data_model>
  <data_model type="com.retek.ride.rule.newmodel.Rule">
    <attribute name="name">
      <value>cmdvmktslsbycsr_ld</value>
    </attribute>
    <attribute name="description">
      <value>a rule</value>
    </attribute>
    <attribute name="creator">
      <value>user</value>
    </attribute>
    <data_model type="java.lang.String">
      <attribute name="name">
        <value>E0</value>
      </attribute>
      <attribute name="formula">
        <value>CMDVMktSlsbyCSR = DRTYMktSlsbyCSR.master</value>
      </attribute>
    </data_model>
  </data_model>
  <data_model type="com.retek.ride.rule.newmodel.Rule">
    <attribute name="name">
      <value>cmlyslsbycsr_ld</value>
    </attribute>
    <attribute name="description">
      <value>a rule</value>
    </attribute>
    <attribute name="creator">
      <value>user</value>
    </attribute>
    <data_model type="java.lang.String">
      <attribute name="name">
        <value>E0</value>
      </attribute>
      <attribute name="formula">
        <value>CMLYSlsbyCSR = CMLYSlsR * ADLYConSegDistV</value>
      </attribute>
    </data_model>
  </data_model>
  <data_model type="com.retek.ride.rule.newmodel.Rule">
    <attribute name="name">
      <value>cmlyslsbycsu_ld</value>
    </attribute>
    <attribute name="description">
      <value>a rule</value>
    </attribute>
    <attribute name="creator">
      <value>user</value>
    </attribute>
    <data_model type="java.lang.String">
      <attribute name="name">
        <value>E0</value>
      </attribute>
      <attribute name="formula">
        <value>CMLYSlsbyCSU = CMLYSlsU * ADLYConSegDistV</value>
      </attribute>
    </data_model>
  </data_model>
  <data_model type="com.retek.ride.rule.newmodel.Rule">
    <attribute name="name">
      <value>cmlypromoslsbycsr_ld</value>
    </attribute>
    <attribute name="description">
      <value>a rule</value>
    </attribute>
    <attribute name="creator">
      <value>user</value>
    </attribute>
    <data_model type="java.lang.String">
      <attribute name="name">
        <value>E0</value>
      </attribute>
      <attribute name="formula">
        <value>CMLYPromoSlsbyCSR = CMLYPromoSlsR * ADLYConSegDistV</value>
      </attribute>
    </data_model>
  </data_model>
  <data_model type="com.retek.ride.rule.newmodel.Rule">
    <attribute name="name">
      <value>cmlymktslsbycsr_ld</value>
    </attribute>
    <attribute name="description">
      <value>a rule</value>
    </attribute>
    <attribute name="creator">
      <value>user</value>
    </attribute>
    <data_model type="java.lang.String">
      <attribute name="name">
        <value>E0</value>
      </attribute>
      <attribute name="formula">
        <value>CMLYMktSlsbyCSR = DRLYMktSlsbyCSR.master</value>
      </attribute>
    </data_model>
  </data_model>
  <data_model type="com.retek.ride.rule.newmodel.Rule">
    <attribute name="name">
      <value>cmdvnumfacingsv_ld</value>
    </attribute>
    <attribute name="description">
      <value>a rule</value>
    </attribute>
    <attribute name="creator">
      <value>user</value>
    </attribute>
    <data_model type="java.lang.String">
      <attribute name="name">
        <value>E0</value>
      </attribute>
      <attribute name="formula">
        <value>CMDVNumFacingsV = CMDVNumFacingsV.master</value>
      </attribute>
    </data_model>
  </data_model>
  <data_model type="com.retek.ride.rule.newmodel.Rule">
    <attribute name="name">
      <value>cmdvshelfcapv_ld</value>
    </attribute>
    <attribute name="description">
      <value>a rule</value>
    </attribute>
    <attribute name="creator">
      <value>user</value>
    </attribute>
    <data_model type="java.lang.String">
      <attribute name="name">
        <value>E0</value>
      </attribute>
      <attribute name="formula">
        <value>CMDVShelfCapV = CMDVShelfCapV.master</value>
      </attribute>
    </data_model>
  </data_model>
  <data_model type="com.retek.ride.rule.newmodel.Rule">
    <attribute name="name">
      <value>cmlysqftv_ld</value>
    </attribute>
    <attribute name="description">
      <value>a rule</value>
    </attribute>
    <attribute name="creator">
      <value>user</value>
    </attribute>
    <data_model type="java.lang.String">
      <attribute name="name">
        <value>E0</value>
      </attribute>
      <attribute name="formula">
        <value>CMLYSqFtV = CMLYSqFtV.master</value>
      </attribute>
    </data_model>
  </data_model>
  <data_model type="com.retek.ride.rule.newmodel.Rule">
    <attribute name="name">
      <value>cmdvsqftv_ld</value>
    </attribute>
    <attribute name="description">
      <value>a rule</value>
    </attribute>
    <attribute name="creator">
      <value>user</value>
    </attribute>
    <data_model type="java.lang.String">
      <attribute name="name">
        <value>E0</value>
      </attribute>
      <attribute name="formula">
        <value>CMDVSqFtV = CMDVSqFtV.master</value>
      </attribute>
    </data_model>
  </data_model>
  <data_model type="com.retek.ride.rule.newmodel.Rule">
    <attribute name="name">
      <value>adwptactictx_ld</value>
    </attribute>
    <attribute name="description">
      <value>a rule</value>
    </attribute>
    <attribute name="creator">
      <value>user</value>
    </attribute>
    <data_model type="java.lang.String">
      <attribute name="name">
        <value>E0</value>
      </attribute>
      <attribute name="formula">
        <value>ADWPTacticTx = ADWPTacticTx.master</value>
      </attribute>
    </data_model>
  </data_model>
  <data_model type="com.retek.ride.rule.newmodel.Rule">
    <attribute name="name">
      <value>cmwpslsar_ld</value>
    </attribute>
    <attribute name="description">
      <value>a rule</value>
    </attribute>
    <attribute name="creator">
      <value>user</value>
    </attribute>
    <data_model type="java.lang.String">
      <attribute name="name">
        <value>E0</value>
      </attribute>
      <attribute name="formula">
        <value>CMWPSlsAr = CMWPSlsR / CMWPSlsU</value>
      </attribute>
    </data_model>
  </data_model>
  <data_model type="com.retek.ride.rule.newmodel.Rule">
    <attribute name="name">
      <value>cmwppromoslsar_ld</value>
    </attribute>
    <attribute name="description">
      <value>a rule</value>
    </attribute>
    <attribute name="creator">
      <value>user</value>
    </attribute>
    <data_model type="java.lang.String">
      <attribute name="name">
        <value>E0</value>
      </attribute>
      <attribute name="formula">
        <value>CMWPPromoSlsAr = CMWPPromoSlsR / CMWPPromoSlsU</value>
      </attribute>
    </data_model>
  </data_model>
  <data_model type="com.retek.ride.rule.newmodel.Rule">
    <attribute name="name">
      <value>cmwppvtlblslsar_ld</value>
    </attribute>
    <attribute name="description">
      <value>a rule</value>
    </attribute>
    <attribute name="creator">
      <value>user</value>
    </attribute>
    <data_model type="java.lang.String">
      <attribute name="name">
        <value>E0</value>
      </attribute>
      <attribute name="formula">
        <value>CMWPPvtLblSlsAr = CMWPPvtLblSlsR / CMWPPvtLblSlsU</value>
      </attribute>
    </data_model>
  </data_model>
  <data_model type="com.retek.ride.rule.newmodel.Rule">
    <attribute name="name">
      <value>cmwppvtlblgpp_ld</value>
    </attribute>
    <attribute name="description">
      <value>a rule</value>
    </attribute>
    <attribute name="creator">
      <value>user</value>
    </attribute>
    <data_model type="java.lang.String">
      <attribute name="name">
        <value>E0</value>
      </attribute>
      <attribute name="formula">
        <value>CMWPPvtLblGPp = CMWPPvtLblGPR / CMWPPvtLblSlsR</value>
      </attribute>
    </data_model>
  </data_model>
  <data_model type="com.retek.ride.rule.newmodel.Rule">
    <attribute name="name">
      <value>addvslsvwgtv_ld</value>
    </attribute>
    <attribute name="description">
      <value>a rule</value>
    </attribute>
    <attribute name="creator">
      <value>user</value>
    </attribute>
    <data_model type="java.lang.String">
      <attribute name="name">
        <value>E0</value>
      </attribute>
      <attribute name="formula">
        <value>ADDVSlsRWgtV = ADDVSlsRWgtV.master</value>
      </attribute>
    </data_model>
  </data_model>
  <data_model type="com.retek.ride.rule.newmodel.Rule">
    <attribute name="name">
      <value>acwpasrtslsr_ld</value>
    </attribute>
    <attribute name="description">
      <value>a rule</value>
    </attribute>
    <attribute name="creator">
      <value>user</value>
    </attribute>
    <data_model type="java.lang.String">
      <attribute name="name">
        <value>E0</value>
      </attribute>
      <attribute name="formula">
        <value>ACWPAsrtSlsR = ACWPAsrtSlsR.master</value>
      </attribute>
    </data_model>
  </data_model>
  <data_model type="com.retek.ride.rule.newmodel.Rule">
    <attribute name="name">
      <value>acwpasrtslsu_ld</value>
    </attribute>
    <attribute name="description">
      <value>a rule</value>
    </attribute>
    <attribute name="creator">
      <value>user</value>
    </attribute>
    <data_model type="java.lang.String">
      <attribute name="name">
        <value>E0</value>
      </attribute>
      <attribute name="formula">
        <value>ACWPAsrtSlsU = ACWPAsrtSlsU.master</value>
      </attribute>
    </data_model>
  </data_model>
  <data_model type="com.retek.ride.rule.newmodel.Rule">
    <attribute name="name">
      <value>acwpasrtproslsr_ld</value>
    </attribute>
    <attribute name="description">
      <value>a rule</value>
    </attribute>
    <attribute name="creator">
      <value>user</value>
    </attribute>
    <data_model type="java.lang.String">
      <attribute name="name">
        <value>E0</value>
      </attribute>
      <attribute name="formula">
        <value>ACWPAsrtProSlsR = ACWPAsrtProSlsR.master</value>
      </attribute>
    </data_model>
  </data_model>
  <data_model type="com.retek.ride.rule.newmodel.Rule">
    <attribute name="name">
      <value>acwpasrtproslsu_ld</value>
    </attribute>
    <attribute name="description">
      <value>a rule</value>
    </attribute>
    <attribute name="creator">
      <value>user</value>
    </attribute>
    <data_model type="java.lang.String">
      <attribute name="name">
        <value>E0</value>
      </attribute>
      <attribute name="formula">
        <value>ACWPAsrtProSlsU = ACWPAsrtProSlsU.master</value>
      </attribute>
    </data_model>
  </data_model>
  <data_model type="com.retek.ride.rule.newmodel.Rule">
    <attribute name="name">
      <value>acwpasrtplslsr_ld</value>
    </attribute>
    <attribute name="description">
      <value>a rule</value>
    </attribute>
    <attribute name="creator">
      <value>user</value>
    </attribute>
    <data_model type="java.lang.String">
      <attribute name="name">
        <value>E0</value>
      </attribute>
      <attribute name="formula">
        <value>ACWPAsrtPLSlsR = ACWPAsrtPLSlsR.master</value>
      </attribute>
    </data_model>
  </data_model>
  <data_model type="com.retek.ride.rule.newmodel.Rule">
    <attribute name="name">
      <value>acwpasrtplslsu_ld</value>
    </attribute>
    <attribute name="description">
      <value>a rule</value>
    </attribute>
    <attribute name="creator">
      <value>user</value>
    </attribute>
    <data_model type="java.lang.String">
      <attribute name="name">
        <value>E0</value>
      </attribute>
      <attribute name="formula">
        <value>ACWPAsrtPLSlsU = ACWPAsrtPLSlsU.master</value>
      </attribute>
    </data_model>
  </data_model>
  <data_model type="com.retek.ride.rule.newmodel.Rule">
    <attribute name="name">
      <value>acwpasrtgpr_ld</value>
    </attribute>
    <attribute name="description">
      <value>a rule</value>
    </attribute>
    <attribute name="creator">
      <value>user</value>
    </attribute>
    <data_model type="java.lang.String">
      <attribute name="name">
        <value>E0</value>
      </attribute>
      <attribute name="formula">
        <value>ACWPAsrtGPR = ACWPAsrtGPR.master</value>
      </attribute>
    </data_model>
  </data_model>
  <data_model type="com.retek.ride.rule.newmodel.Rule">
    <attribute name="name">
      <value>acwpasrtplgpr_ld</value>
    </attribute>
    <attribute name="description">
      <value>a rule</value>
    </attribute>
    <attribute name="creator">
      <value>user</value>
    </attribute>
    <data_model type="java.lang.String">
      <attribute name="name">
        <value>E0</value>
      </attribute>
      <attribute name="formula">
        <value>ACWPAsrtPLGPR = ACWPAsrtPLGPR.master</value>
      </attribute>
    </data_model>
  </data_model>
  <data_model type="com.retek.ride.rule.newmodel.Rule">
    <attribute name="name">
      <value>accpasrtslsr_ld</value>
    </attribute>
    <attribute name="description">
      <value>a rule</value>
    </attribute>
    <attribute name="creator">
      <value>user</value>
    </attribute>
    <data_model type="java.lang.String">
      <attribute name="name">
        <value>E0</value>
      </attribute>
      <attribute name="formula">
        <value>ACCPAsrtSlsR = ACCPAsrtSlsR.master</value>
      </attribute>
    </data_model>
  </data_model>
  <data_model type="com.retek.ride.rule.newmodel.Rule">
    <attribute name="name">
      <value>accpasrtslsu_ld</value>
    </attribute>
    <attribute name="description">
      <value>a rule</value>
    </attribute>
    <attribute name="creator">
      <value>user</value>
    </attribute>
    <data_model type="java.lang.String">
      <attribute name="name">
        <value>E0</value>
      </attribute>
      <attribute name="formula">
        <value>ACCPAsrtSlsU = ACCPAsrtSlsU.master</value>
      </attribute>
    </data_model>
  </data_model>
  <data_model type="com.retek.ride.rule.newmodel.Rule">
    <attribute name="name">
      <value>accpasrtproslsr_ld</value>
    </attribute>
    <attribute name="description">
      <value>a rule</value>
    </attribute>
    <attribute name="creator">
      <value>user</value>
    </attribute>
    <data_model type="java.lang.String">
      <attribute name="name">
        <value>E0</value>
      </attribute>
      <attribute name="formula">
        <value>ACCPAsrtProSlsR = ACCPAsrtProSlsR.master</value>
      </attribute>
    </data_model>
  </data_model>
  <data_model type="com.retek.ride.rule.newmodel.Rule">
    <attribute name="name">
      <value>accpasrtproslsu_ld</value>
    </attribute>
    <attribute name="description">
      <value>a rule</value>
    </attribute>
    <attribute name="creator">
      <value>user</value>
    </attribute>
    <data_model type="java.lang.String">
      <attribute name="name">
        <value>E0</value>
      </attribute>
      <attribute name="formula">
        <value>ACCPAsrtProSlsU = ACCPAsrtProSlsU.master</value>
      </attribute>
    </data_model>
  </data_model>
  <data_model type="com.retek.ride.rule.newmodel.Rule">
    <attribute name="name">
      <value>accpasrtplslsr_ld</value>
    </attribute>
    <attribute name="description">
      <value>a rule</value>
    </attribute>
    <attribute name="creator">
      <value>user</value>
    </attribute>
    <data_model type="java.lang.String">
      <attribute name="name">
        <value>E0</value>
      </attribute>
      <attribute name="formula">
        <value>ACCPAsrtPLSlsR = ACCPAsrtPLSlsR.master</value>
      </attribute>
    </data_model>
  </data_model>
  <data_model type="com.retek.ride.rule.newmodel.Rule">
    <attribute name="name">
      <value>accpasrtplslsu_ld</value>
    </attribute>
    <attribute name="description">
      <value>a rule</value>
    </attribute>
    <attribute name="creator">
      <value>user</value>
    </attribute>
    <data_model type="java.lang.String">
      <attribute name="name">
        <value>E0</value>
      </attribute>
      <attribute name="formula">
        <value>ACCPAsrtPLSlsU = ACCPAsrtPLSlsU.master</value>
      </attribute>
    </data_model>
  </data_model>
  <data_model type="com.retek.ride.rule.newmodel.Rule">
    <attribute name="name">
      <value>accpasrtgpr_ld</value>
    </attribute>
    <attribute name="description">
      <value>a rule</value>
    </attribute>
    <attribute name="creator">
      <value>user</value>
    </attribute>
    <data_model type="java.lang.String">
      <attribute name="name">
        <value>E0</value>
      </attribute>
      <attribute name="formula">
        <value>ACCPAsrtGPR = ACCPAsrtGPR.master</value>
      </attribute>
    </data_model>
  </data_model>
  <data_model type="com.retek.ride.rule.newmodel.Rule">
    <attribute name="name">
      <value>accpasrtplgpr_ld</value>
    </attribute>
    <attribute name="description">
      <value>a rule</value>
    </attribute>
    <attribute name="creator">
      <value>user</value>
    </attribute>
    <data_model type="java.lang.String">
      <attribute name="name">
        <value>E0</value>
      </attribute>
      <attribute name="formula">
        <value>ACCPAsrtPLGPR = ACCPAsrtPLGPR.master</value>
      </attribute>
    </data_model>
  </data_model>
  <data_model type="com.retek.ride.rule.newmodel.Rule">
    <attribute name="name">
      <value>acwpcarriedb_ld</value>
    </attribute>
    <attribute name="description">
      <value>a rule</value>
    </attribute>
    <attribute name="creator">
      <value>user</value>
    </attribute>
    <data_model type="java.lang.String">
      <attribute name="name">
        <value>E0</value>
      </attribute>
      <attribute name="formula">
        <value>ACWPCarriedB = ACWPCarriedB.master</value>
      </attribute>
    </data_model>
  </data_model>
  <data_model type="com.retek.ride.rule.newmodel.Rule">
    <attribute name="name">
      <value>accpcarriedb_ld</value>
    </attribute>
    <attribute name="description">
      <value>a rule</value>
    </attribute>
    <attribute name="creator">
      <value>user</value>
    </attribute>
    <data_model type="java.lang.String">
      <attribute name="name">
        <value>E0</value>
      </attribute>
      <attribute name="formula">
        <value>ACCPCarriedB = ACCPCarriedB.master</value>
      </attribute>
    </data_model>
  </data_model>
  <data_model type="com.retek.ride.rule.newmodel.Rule">
    <attribute name="name">
      <value>aclyasrtskuct_ld</value>
    </attribute>
    <attribute name="description">
      <value>a rule</value>
    </attribute>
    <attribute name="creator">
      <value>user</value>
    </attribute>
    <data_model type="java.lang.String">
      <attribute name="name">
        <value>E0</value>
      </attribute>
      <attribute name="formula">
        <value>ACLYAsrtSkuCt &lt;- timeshift(ACCPAsrtSkuCt.master, ADLYWeekMapTx.master)</value>
      </attribute>
    </data_model>
  </data_model>
  <data_model type="com.retek.ride.rule.newmodel.Rule">
    <attribute name="name">
      <value>aclyasrtcoreb_ld</value>
    </attribute>
    <attribute name="description">
      <value>a rule</value>
    </attribute>
    <attribute name="creator">
      <value>user</value>
    </attribute>
    <data_model type="java.lang.String">
      <attribute name="name">
        <value>E0</value>
      </attribute>
      <attribute name="formula">
        <value>ACLYAsrtCoreB &lt;- timeshift(ACCPAsrtCoreB.master, ADLYWeekMapTx.master )</value>
      </attribute>
    </data_model>
  </data_model>
  <data_model type="com.retek.ride.rule.newmodel.Rule">
    <attribute name="name">
      <value>aclyasrtoptnb_ld</value>
    </attribute>
    <attribute name="description">
      <value>a rule</value>
    </attribute>
    <attribute name="creator">
      <value>user</value>
    </attribute>
    <data_model type="java.lang.String">
      <attribute name="name">
        <value>E0</value>
      </attribute>
      <attribute name="formula">
        <value>ACLYAsrtOptnB &lt;- timeshift(ACCPAsrtOptnB.master, ADLYWeekMapTx.master )</value>
      </attribute>
    </data_model>
  </data_model>
  <data_model type="com.retek.ride.rule.newmodel.Rule">
    <attribute name="name">
      <value>aclymandb_ld</value>
    </attribute>
    <attribute name="description">
      <value>a rule</value>
    </attribute>
    <attribute name="creator">
      <value>user</value>
    </attribute>
    <data_model type="java.lang.String">
      <attribute name="name">
        <value>E0</value>
      </attribute>
      <attribute name="formula">
        <value>ACLYMandB &lt;- timeshift(ACCPMandB.master, ADLYWeekMapTx.master )</value>
      </attribute>
    </data_model>
  </data_model>
  <data_model type="com.retek.ride.rule.newmodel.Rule">
    <attribute name="name">
      <value>aclypvtlblslsr_ld</value>
    </attribute>
    <attribute name="description">
      <value>a rule</value>
    </attribute>
    <attribute name="creator">
      <value>user</value>
    </attribute>
    <data_model type="java.lang.String">
      <attribute name="name">
        <value>E0</value>
      </attribute>
      <attribute name="formula">
        <value>ACLYPvtLblSlsR &lt;- timeshift(ACWPPvtLblSlsR.master, ADLYWeekMapTx.master )</value>
      </attribute>
    </data_model>
  </data_model>
  <data_model type="com.retek.ride.rule.newmodel.Rule">
    <attribute name="name">
      <value>aclypromoslsr_ld</value>
    </attribute>
    <attribute name="description">
      <value>a rule</value>
    </attribute>
    <attribute name="creator">
      <value>user</value>
    </attribute>
    <data_model type="java.lang.String">
      <attribute name="name">
        <value>E0</value>
      </attribute>
      <attribute name="formula">
        <value>ACLYPromoSlsR &lt;- timeshift(ACWPPromoSlsR.master, ADLYWeekMapTx.master)</value>
      </attribute>
    </data_model>
  </data_model>
  <data_model type="com.retek.ride.rule.newmodel.Rule">
    <attribute name="name">
      <value>cmoptacticassigntx_ld</value>
    </attribute>
    <attribute name="description">
      <value>a rule</value>
    </attribute>
    <attribute name="creator">
      <value>user</value>
    </attribute>
    <data_model type="java.lang.String">
      <attribute name="name">
        <value>E0</value>
      </attribute>
      <attribute name="formula">
        <value>CMOPTacticAssgnTx = CMOPTacticAssgnTx.master</value>
      </attribute>
    </data_model>
  </data_model>
  <data_model type="com.retek.ride.rule.newmodel.Rule">
    <attribute name="name">
      <value>addvconsegdistv_ld</value>
    </attribute>
    <attribute name="description">
      <value>a rule</value>
    </attribute>
    <attribute name="creator">
      <value>user</value>
    </attribute>
    <data_model type="java.lang.String">
      <attribute name="name">
        <value>E0</value>
      </attribute>
      <attribute name="formula">
        <value>ADDVConSegDistV = if (DRTYConSegDistV.level([prod].top) == 0, ADLYConSegDistV, DRTYConSegDistV)</value>
      </attribute>
    </data_model>
  </data_model>
  <data_model type="com.retek.ride.rule.newmodel.Rule">
    <attribute name="name">
      <value>cmdvtacticb_ld</value>
    </attribute>
    <attribute name="description">
      <value>a rule</value>
    </attribute>
    <attribute name="creator">
      <value>user</value>
    </attribute>
    <data_model type="java.lang.String">
      <attribute name="name">
        <value>E0</value>
      </attribute>
      <attribute name="formula">
        <value>CMDVTacticB = CMDVTacticB.master</value>
      </attribute>
    </data_model>
  </data_model>
  <data_model type="com.retek.ride.rule.newmodel.Rule">
    <attribute name="name">
      <value>cmwpturnrr_ld</value>
    </attribute>
    <attribute name="description">
      <value>a rule</value>
    </attribute>
    <attribute name="creator">
      <value>user</value>
    </attribute>
    <data_model type="java.lang.String">
      <attribute name="name">
        <value>E0</value>
      </attribute>
      <attribute name="formula">
        <value>CMWPTurnRr =  tssum(CMWPSlsR) / CMWPAvgInvR</value>
      </attribute>
    </data_model>
  </data_model>
  <data_model type="com.retek.ride.rule.newmodel.Rule">
    <attribute name="name">
      <value>CMWPTacticNotesTx_ld</value>
    </attribute>
    <attribute name="description">
      <value>a rule</value>
    </attribute>
    <attribute name="creator">
      <value>user</value>
    </attribute>
    <data_model type="java.lang.String">
      <attribute name="name">
        <value>E0</value>
      </attribute>
      <attribute name="formula">
        <value>CMWPTacticNotesTx = CMWPTacticNotesTx.master</value>
      </attribute>
    </data_model>
  </data_model>
  <data_model type="com.retek.ride.rule.newmodel.Rule">
    <attribute name="name">
      <value>CMLYTacticNotesTx_ld</value>
    </attribute>
    <attribute name="description">
      <value>a rule</value>
    </attribute>
    <attribute name="creator">
      <value>user</value>
    </attribute>
    <data_model type="java.lang.String">
      <attribute name="name">
        <value>E0</value>
      </attribute>
      <attribute name="formula">
        <value>CMLYTacticNotesTx &lt;- timeshift (CMWPTacticNotesTx.master, ADLYQrtrMapTx.master)</value>
      </attribute>
    </data_model>
  </data_model>
  <data_model type="com.retek.ride.rule.newmodel.Rule">
    <attribute name="name">
      <value>CMOPTacticNotesTx_ld</value>
    </attribute>
    <attribute name="description">
      <value>a rule</value>
    </attribute>
    <attribute name="creator">
      <value>user</value>
    </attribute>
    <data_model type="java.lang.String">
      <attribute name="name">
        <value>E0</value>
      </attribute>
      <attribute name="formula">
        <value>CMOPTacticNotesTx = CMOPTacticNotesTx.master</value>
      </attribute>
    </data_model>
  </data_model>
  <data_model type="com.retek.ride.rule.newmodel.Rule">
    <attribute name="name">
      <value>drtyconsegdistv_ld</value>
    </attribute>
    <attribute name="description">
      <value>a rule</value>
    </attribute>
    <attribute name="creator">
      <value>user</value>
    </attribute>
    <data_model type="java.lang.String">
      <attribute name="name">
        <value>E0</value>
      </attribute>
      <attribute name="formula">
        <value>DRTYConSegDistV = DRTYConSegDistV.master</value>
      </attribute>
    </data_model>
  </data_model>
  <data_model type="com.retek.ride.rule.newmodel.Rule">
    <attribute name="name">
      <value>adlyconsegdistv_ld</value>
    </attribute>
    <attribute name="description">
      <value>a rule</value>
    </attribute>
    <attribute name="creator">
      <value>user</value>
    </attribute>
    <data_model type="java.lang.String">
      <attribute name="name">
        <value>E0</value>
      </attribute>
      <attribute name="formula">
        <value>ADLYConSegDistV &lt;- timeshift(DRTYConSegDistV.master, ADLYQrtrMapTx.master)</value>
      </attribute>
    </data_model>
  </data_model>
  <data_model type="com.retek.ride.rule.newmodel.Rule">
    <attribute name="name">
      <value>cmwpgpp_ld</value>
    </attribute>
    <attribute name="description">
      <value>a rule</value>
    </attribute>
    <attribute name="creator">
      <value>user</value>
    </attribute>
    <data_model type="java.lang.String">
      <attribute name="name">
        <value>E0</value>
      </attribute>
      <attribute name="formula">
        <value>CMWPGPp = CMWPGPR / CMWPSlsR</value>
      </attribute>
    </data_model>
  </data_model>
</data_set>
